main.py
cryptopanic_mcp_server-0.1.0.dist-info/licenses/LICENSE
cryptopanic_mcp_server-0.1.0.dist-info/METADATA
cryptopanic_mcp_server-0.1.0.dist-info/WHEEL
cryptopanic_mcp_server-0.1.0.dist-info/top_level.txt
cryptopanic_mcp_server-0.1.0.dist-info/RECORD
