Metadata-Version: 2.4
Name: cryptopanic-mcp-server
Version: 0.1.0
Summary: Provide the latest cryptocurrency news for AI agents.
Requires-Python: >=3.13
License-File: LICENSE
Requires-Dist: dotenv>=0.9.9
Requires-Dist: mcp[cli]>=1.3.0
Requires-Dist: requests>=2.32.3
Dynamic: license-file
